spellcheckmate/__init__.py
spellcheckmate/big.txt
spellcheckmate/spellcheckmate.py
spellcheckmate-0.1.4.dist-info/METADATA
spellcheckmate-0.1.4.dist-info/WHEEL
spellcheckmate-0.1.4.dist-info/RECORD
