Metadata-Version: 2.1
Name: spellcheckmate
Version: 0.1.4
Summary: A hopefully cross-platform reimplementation of Peter Norvig's spelling corrector.
License: MIT
Author: Csaba Szallós Kis
Requires-Python: >=3.10,<4.0
Classifier: License :: OSI Approved :: MIT License
Classifier: Programming Language :: Python :: 3
Classifier: Programming Language :: Python :: 3.10
Classifier: Programming Language :: Python :: 3.11
Classifier: Programming Language :: Python :: 3.12
